limiter_for_sanic/__init__.py
limiter_for_sanic/bulk.py
limiter_for_sanic/errors.py
limiter_for_sanic/lua.py
limiter_for_sanic-0.1.0.dist-info/METADATA
limiter_for_sanic-0.1.0.dist-info/WHEEL
limiter_for_sanic-0.1.0.dist-info/top_level.txt
limiter_for_sanic-0.1.0.dist-info/RECORD
