Metadata-Version: 2.1
Name: limiter-for-sanic
Version: 0.1.0
Summary: Limiter for Sanic.
Home-page: https://github.com/kingchao1024/sanic_limiter
Author: kingchao
Author-email: kingchao1024@gmail.com
License: MIT
Classifier: License :: OSI Approved :: MIT License
Classifier: Programming Language :: Python :: 3
Classifier: Programming Language :: Python :: 3.7
Requires-Python: >=3.7
Requires-Dist: aioredis (==2.0.1)
Requires-Dist: sanic (==22.9.1)
